square_elk_json_formatter/ElkJsonFormatter.py
square_elk_json_formatter/__init__.py
square_elk_json_formatter-0.0.3.dist-info/METADATA
square_elk_json_formatter-0.0.3.dist-info/WHEEL
square_elk_json_formatter-0.0.3.dist-info/top_level.txt
square_elk_json_formatter-0.0.3.dist-info/RECORD
