Metadata-Version: 2.1
Name: square-elk-json-formatter
Version: 0.0.3
Summary: UNKNOWN
Home-page: https://github.com/UKP-SQuARE/square-elk-json-formatter
Author: UKP
Author-email: baumgaertner@ukp.informatik.tu-darmstadt.de
License: MIT
Download-URL: https://github.com/UKP-SQuARE/square-elk-json-formatter/archive/refs/tags/v0.0.3.tar.gz
Platform: UNKNOWN
Requires-Dist: python-json-logger (==2.0.1)
